NudeNetv2/__init__.py
NudeNetv2/classifier.py
NudeNetv2/detector.py
NudeNetv2/detector_utils.py
NudeNetv2/image_utils.py
NudeNetv2/lite_classifier.py
NudeNetv2/test.py
NudeNetv2/video_utils.py
nudenet/__init__.py
nudenet/classifier.py
nudenet/detector.py
nudenet/detector_utils.py
nudenet/image_utils.py
nudenet/lite_classifier.py
nudenet/video_utils.py
NudeNetv2-2.0.11.dist-info/LICENSE.md
NudeNetv2-2.0.11.dist-info/METADATA
NudeNetv2-2.0.11.dist-info/WHEEL
NudeNetv2-2.0.11.dist-info/top_level.txt
NudeNetv2-2.0.11.dist-info/RECORD
